Workbook
Name data: Table4[]
Name NativeTimeline_Date: #N/A
Name Slicer_Category: #N/A

Sheet SALES DATA 
A1: MS EXCEL DATA ANALYTICS — SALES REPORT
A2: 100 Records | Sales Performance Analysis | 2025
A4: Order ID | B4: Date | C4: Region | D4: Salesperson | E4: Product | F4: Category | G4: Quantity | H4: Unit Price | I4: Discount % | J4: Sales | K4: Cost | L4: Profit
A5: ORD-001 | B5: 45659 | C5: East | D5: Rahul | E5: Laptop | F5: Electronics | G5: 2 | H5: 688.07 | I5: 0.15 | J5: 1169.72 | K5: 882.52 | L5: 287.2
A6: ORD-002 | B6: 45668 | C6: South | D6: Priya | E6: Laptop | F6: Electronics | G6: 13 | H6: 590.04 | I6: 0.02 | J6: 7517.11 | K6: 4723.42 | L6: 2793.69
A7: ORD-003 | B7: 45668 | C7: South | D7: Priya | E7: Tablet | F7: Electronics | G7: 8 | H7: 325.59 | I7: 0.02 | J7: 2552.63 | K7: 1487.63 | L7: 1065
A8: ORD-004 | B8: 45671 | C8: South | D8: Arjun | E8: Laptop | F8: Electronics | G8: 1 | H8: 600.23 | I8: 0.02 | J8: 588.23 | K8: 430.23 | L8: 158
A9: ORD-005 | B9: 45674 | C9: East | D9: Simran | E9: Laptop | F9: Electronics | G9: 2 | H9: 700.02 | I9: 0 | J9: 1400.04 | K9: 875.8 | L9: 524.24
A10: ORD-006 | B10: 45677 | C10: West | D10: Priya | E10: Printer | F10: Electronics | G10: 3 | H10: 197.43 | I10: 0 | J10: 592.29 | K10: 400.53 | L10: 191.76
A11: ORD-007 | B11: 45678 | C11: East | D11: Priya | E11: Keyboard | F11: Accessories | G11: 1 | H11: 43.97 | I11: 0.15 | J11: 37.37 | K11: 38.29 | L11: -0.92
A12: ORD-008 | B12: 45688 | C12: South | D12: Arjun | E12: Desk | F12: Furniture | G12: 8 | H12: 285.7 | I12: 0.15 | J12: 1942.76 | K12: 1559.56 | L12: 383.2
A13: ORD-009 | B13: 45695 | C13: North | D13: Meera | E13: Desk | F13: Furniture | G13: 3 | H13: 299.02 | I13: 0.05 | J13: 852.21 | K13: 628.74 | L13: 223.47
A14: ORD-010 | B14: 45696 | C14: West | D14: Simran | E14: Keyboard | F14: Accessories | G14: 7 | H14: 42.56 | I14: 0.08 | J14: 274.09 | K14: 188.42 | L14: 85.67
A15: ORD-011 | B15: 45705 | C15: West | D15: Simran | E15: Printer | F15: Electronics | G15: 3 | H15: 171.69 | I15: 0.15 | J15: 437.81 | K15: 340.5 | L15: 97.31
A16: ORD-012 | B16: 45705 | C16: South | D16: Rahul | E16: Laptop | F16: Electronics | G16: 11 | H16: 747.38 | I16: 0.15 | J16: 6988 | K16: 4561.69 | L16: 2426.31
... A104: ORD-100 | B104: 46020 | C104: South | D104: Karan | E104: Mouse | F104: Accessories | G104: 5 | H104: 23.92 | I104: 0.02 | J104: 117.21 | K104: 77.71 | L104: 39.5

Sheet FORMULA SHEET
A1: EXCEL FORMULA PRACTICE
A3: Function | B3: Example Formula | C3: Purpose | D3: Note
A4: SUM | B4: =SUM(Table4[Sales]) -> 158716.62 | C4: Total Sales | D4: Adds sales
A5: AVERAGE | B5: =AVERAGE(Table4[Sales]) -> 1587.1662 | C5: Average Sales | D5: Average order
A6: MAX | B6: =MAX(Table4[Profit]) -> 3127.89 | C6: Maximum Profit | D6: Highest profit
A7: MIN | B7: =MIN(Table4[Profit]) -> -0.92 | C7: Minimum Profit | D7: Lowest profit
A8: COUNT | B8: =COUNT(Table4[Quantity]) -> 100 | C8: Count Quantity | D8: Counts numbers
A9: COUNTA | B9: =COUNTA(Table4[Order ID]) -> 100 | C9: Count Orders | D9: Counts non-empty
A10: COUNTIF | B10: =COUNTIF(Table4[Region],"North") -> 20 | C10: North Orders | D10: One condition
A11: COUNTIFS | B11: =COUNTIFS(Table4[Region],"North",Table4[Category],"Electronics") -> 6 | C11: North Electronics | D11: Multiple conditions
A12: SUMIF | B12: =SUMIF(Table4[Region],"North",Table4[Sales]) -> 35888.77 | C12: North Sales | D12: One condition
A13: SUMIFS | B13: =SUMIFS(Table4[Sales],Table4[Region],"North",Table4[Category],"Electronics") -> 18740.58 | C13: North Electronics Sales | D13: Multiple conditions
A14: AVERAGEIF | B14: =AVERAGEIF(Table4[Region],"North",Table4[Sales]) -> 1794.4385 | C14: Average North Sales | D14: One condition
A15: AVERAGEIFS | B15: =AVERAGEIFS(Table4[Sales],Table4[Region],"North",Table4[Category],"Electronics") -> 3123.43 | C15: Average North Electronics | D15: Multiple conditions
A16: IF | B16: =IF('SALES DATA '!L5>0,"Profit","loss") -> Profit | C16: Profit/Loss | D16: Logical test
A17: IFS | B17: {=_xlfn.IFS('SALES DATA '!L5>1000,"High",'SALES DATA '!L5>500,"Medium",TRUE,"Low")} -> Low | C17: Profit Band | D17: Multiple tests
A18: IFERROR | B18: =IFERROR('SALES DATA '!J5/'SALES DATA '!K5,0) -> 1.3254317 | C18: Safe Calculation | D18: Handles errors
A19: AND | B19: =AND('SALES DATA '!C5="East",'SALES DATA '!F5="Electronics") -> TRUE | C19: Two Conditions | D19: Both true
A20: OR | B20: =OR('SALES DATA '!C5="North",'SALES DATA '!F5="Electronics") -> TRUE | C20: Alternative Conditions | D20: Either true
A21: NOT | B21: =NOT('SALES DATA '!C5="north") -> TRUE | C21: Reverse Condition | D21: Not North
A22: ROUND | B22: =ROUND(B18,2) -> 1.33 | C22: Rounded Sales | D22: Rounds value
A23: TODAY | B23: =TODAY() -> 46257 | C23: Current Date | D23: Today's date
A24: YEAR | B24: =YEAR(B23) -> 2026 | C24: Year | D24: Extract year
A25: MONTH | B25: =MONTH(B23) -> 8 | C25: Month | D25: Extract month
A26: TEXT | B26: =TEXT(B23,"mmm-yyyy") -> Aug-2026 | C26: Month Label | D26: Formats date
A27: LEFT | B27: =LEFT(C27,3) -> Lef | C27: Left Characters | D27: First 3 chars
A28: RIGHT | B28: =RIGHT(C28,3) -> ers | C28: Right Characters | D28: Last 3 chars
A29: MID | B29: =MID(C29,3,4) -> ddle | C29: Middle Characters | D29: Extracts middle
A30: LEN | B30: =LEN(C30) -> 11 | C30: Text Length | D30: Counts chars
A31: TRIM | B31: =TRIM(C31) -> Clean Spaces | C31: Clean Spaces | D31: Removes extra spaces
A32: UPPER | B32: =UPPER(C32) -> UPPERCASE | C32: Uppercase | D32: Converts case
A33: LOWER | B33: =LOWER(C33) -> lowercase | C33: Lowercase | D33: Converts case
A34: PROPER | B34: =PROPER(C34) -> Proper Case | C34: Proper Case | D34: Capitalizes words
A35: CONCAT | B35: =_xlfn.CONCAT(C35,D35) -> Join TextCombines text | C35: Join Text | D35: Combines text
A36: TEXTJOIN | B36: =_xlfn.TEXTJOIN("/",TRUE,C36,D36) -> Join Multiple Text/Uses separator | C36: Join Multiple Text | D36: Uses separator
A37: VLOOKUP | B37: =VLOOKUP('SALES DATA '!A5,Table4[],12, FALSE) -> 287.2 | C37: Lookup Profit | D37: Vertical lookup
A38: XLOOKUP | B38: =_xlfn.XLOOKUP('SALES DATA '!A5,A5:A104,L5:L104,"Not Found") -> Not Found | C38: Find Profit | D38: Modern lookup
A39: INDEX + MATCH | B39: =INDEX(Table4[Profit],MATCH(A5,Table4[Order ID],0)) -> #N/A | C39: Find Profit | D39: Flexible lookup

Sheet PIVOT TABLES
A1: PIVOT TABLES
A4: REGION-WISE SALES | E4: CATEGORY-WISE PROFIT | I4: MONTHLY SALES | M4: SALESPERSON WISE SALES
A5: Row Labels | B5: Sum of Sales | E5: Row Labels | F5: Sum of Profit | I5: Row Labels | J5: Sum of Sales | M5: Row Labels | N5: Sum of Sales
A6: East | B6: 41599.16 | E6: Accessories | F6: 4853.5 | I6: Jan | J6: 15800.15 | M6: Aarav | N6: 10576.33
A7: North | B7: 35888.77 | E7: Electronics | F7: 28835.31 | I7: Feb | J7: 8942.96 | M7: Arjun | N7: 26816.55
A8: North | B8: 852.21 | E8: Furniture | F8: 8910.14 | I8: Mar | J8: 7562.97 | M8: Karan | N8: 21094.65
A9: South | B9: 40274.71 | E9: Grand Total | F9: 42598.95 | I9: Apr | J9: 16577.04 | M9: Meera | N9: 21765.91
A10: West | B10: 40101.77 | I10: May | J10: 17896.26 | M10: Neha | N10: 4288.91
A11: Grand Total | B11: 158716.62 | I11: Jun | J11: 11173.07 | M11: Priya | N11: 35899.42
A12: PRODUCT COST AND PROFIT | E12: Sum of Sales | G12: Sum of Cost | I12: Jul | J12: 31072.09 | M12: Rahul | N12: 20839.65
E13: 158716.62 | G13: 116117.67 | I13: Aug | J13: 11546.49 | M13: Simran | N13: 17435.2
A14: #VALUE! | I14: Sep | J14: 2645.41 | M14: Grand Total | N14: 158716.62
I15: Oct | J15: 19380.16
E16: Sum of Profit | G16: Sum of Quantity | I16: Nov | J16: 11690.59
E17: 42598.95 | G17: 814 | I17: Dec | J17: 4429.43
I18: Grand Total | J18: 158716.62
A21: Row Labels | B21: Sum of Unit Price
A22: Desk | B22: 3517.89
A23: Headset | B23: 744.19
A24: Keyboard | B24: 504.21
A25: Laptop | B25: 9166.2
A26: Monitor | B26: 1633.81
A27: Mouse | B27: 279.2
A28: Office Chair | B28: 423.1
A29: Printer | B29: 1819.54
A30: Tablet | B30: 3198.99
A31: Webcam | B31: 936.32
A32: Grand Total | B32: 22223.45

Sheet DASHBOARD
A1: DASHBOARD
B14: MONTHLY SALES | E14: SALESPERSONS SALES | H14: PRODUCTS COST AND PROFIT
B15: Row Labels | C15: Sum of Sales | E15: Row Labels | F15: Sum of Sales | H15: Row Labels | I15: Sum of Cost | J15: Sum of Profit
B16: Jan | C16: 15800.15 | E16: Aarav | F16: 10576.33 | H16: Desk | I16: 20646.12 | J16: 7972.48
B17: Feb | C17: 8942.96 | E17: Arjun | F17: 26816.55 | H17: Headset | I17: 3499.74 | J17: 1261.12
B18: Mar | C18: 7562.97 | E18: Karan | F18: 21094.65 | H18: Keyboard | I18: 2790.22 | J18: 1007.41
B19: Apr | C19: 16577.04 | E19: Meera | F19: 21765.91 | H19: Laptop | I19: 38711.36 | J19: 14934
B20: May | C20: 17896.26 | E20: Neha | F20: 4288.91 | H20: Monitor | I20: 11813.18 | J20: 3161.14
B21: Jun | C21: 11173.07 | E21: Priya | F21: 35899.42 | H21: Mouse | I21: 1582.57 | J21: 506.15
B22: Jul | C22: 31072.09 | E22: Rahul | F22: 20839.65 | H22: Office Chair | I22: 3899.58 | J22: 937.66
B23: Aug | C23: 11546.49 | E23: Simran | F23: 17435.2 | H23: Printer | I23: 8970.33 | J23: 3671.74
B24: Sep | C24: 2645.41 | E24: Grand Total | F24: 158716.62 | H24: Tablet | I24: 18253.19 | J24: 7068.43
B25: Oct | C25: 19380.16 | H25: Webcam | I25: 5951.38 | J25: 2078.82
B26: Nov | C26: 11690.59 | H26: Grand Total | I26: 116117.67 | J26: 42598.95
B27: Dec | C27: 4429.43
B28: Grand Total | C28: 158716.62
